pyxel/LICENSE
pyxel/__init__.py
pyxel/__init__.pyi
pyxel/__main__.py
pyxel/cli.py
pyxel/editor/__init__.py
pyxel/editor/app.py
pyxel/editor/assets/editor_220x160.png
pyxel/editor/canvas_panel.py
pyxel/editor/editor_base.py
pyxel/editor/extensions.py
pyxel/editor/field_cursor.py
pyxel/editor/image_editor.py
pyxel/editor/image_viewer.py
pyxel/editor/music_editor.py
pyxel/editor/music_field.py
pyxel/editor/octave_bar.py
pyxel/editor/piano_keyboard.py
pyxel/editor/piano_roll.py
pyxel/editor/settings.py
pyxel/editor/sound_editor.py
pyxel/editor/sound_field.py
pyxel/editor/sound_selector.py
pyxel/editor/tilemap_editor.py
pyxel/editor/tilemap_viewer.py
pyxel/editor/widgets/__init__.py
pyxel/editor/widgets/button.py
pyxel/editor/widgets/color_picker.py
pyxel/editor/widgets/image_button.py
pyxel/editor/widgets/image_toggle_button.py
pyxel/editor/widgets/number_picker.py
pyxel/editor/widgets/radio_button.py
pyxel/editor/widgets/scroll_bar.py
pyxel/editor/widgets/settings.py
pyxel/editor/widgets/text_button.py
pyxel/editor/widgets/toggle_button.py
pyxel/editor/widgets/widget.py
pyxel/editor/widgets/widget_var.py
pyxel/examples/01_hello_pyxel.py
pyxel/examples/02_jump_game.py
pyxel/examples/03_draw_api.py
pyxel/examples/04_sound_api.py
pyxel/examples/05_color_palette.py
pyxel/examples/06_click_game.py
pyxel/examples/07_snake.py
pyxel/examples/08_triangle_api.py
pyxel/examples/09_shooter.py
pyxel/examples/10_platformer.py
pyxel/examples/11_offscreen.py
pyxel/examples/12_perlin_noise.py
pyxel/examples/13_custom_font.py
pyxel/examples/14_synthesizer.py
pyxel/examples/15_tiled_map_file.py
pyxel/examples/16_transform.py
pyxel/examples/17_app_launcher.py
pyxel/examples/99_flip_animation.py
pyxel/examples/apps/30sec_of_daylight.pyxapp
pyxel/examples/apps/8bit-bgm-gen.pyxapp
pyxel/examples/apps/cursed_caverns.pyxapp
pyxel/examples/apps/laser-jetman.pyxapp
pyxel/examples/apps/mega_wing.pyxapp
pyxel/examples/apps/megaball.pyxapp
pyxel/examples/apps/space_rescue.pyxapp
pyxel-2.6.1.dist-info/METADATA
pyxel-2.6.1.dist-info/WHEEL
pyxel-2.6.1.dist-info/entry_points.txt
pyxel-2.6.1.dist-info/licenses/pyxel/LICENSE
pyxel-2.6.1.dist-info/RECORD
