Metadata-Version: 2.4
Name: pyxel
Version: 2.6.1
Classifier: Development Status :: 5 - Production/Stable
Classifier: License :: OSI Approved :: MIT License
Classifier: Operating System :: MacOS
Classifier: Operating System :: Microsoft :: Windows
Classifier: Operating System :: POSIX :: Linux
Classifier: Programming Language :: Python
Classifier: Programming Language :: Rust
Classifier: Topic :: Games/Entertainment
Classifier: Topic :: Multimedia :: Graphics
Classifier: Topic :: Multimedia :: Sound/Audio
License-File: pyxel/LICENSE
Summary: A retro game engine for Python
Keywords: game,gamedev
Author-email: Takashi Kitao <takashi.kitao@gmail.com>
Requires-Python: >=3.8
Project-URL: Changelog, https://github.com/kitao/pyxel/blob/main/CHANGELOG.md
Project-URL: Homepage, https://github.com/kitao/pyxel
Project-URL: Repository, https://github.com/kitao/pyxel.git
